LICENSE
MANIFEST.in
README.md
setup.py
genres/__init__.py
genres/api.py
genres/data.txt
genres/db.py
genres/finder.py
genres.egg-info/PKG-INFO
genres.egg-info/SOURCES.txt
genres.egg-info/dependency_links.txt
genres.egg-info/not-zip-safe
genres.egg-info/top_level.txt
requirements/tests.txt